AUTHORS.rst
CHANGELOG.rst
LICENSE
MANIFEST.in
README.rst
setup.py
django_moderator.egg-info/PKG-INFO
django_moderator.egg-info/SOURCES.txt
django_moderator.egg-info/dependency_links.txt
django_moderator.egg-info/not-zip-safe
django_moderator.egg-info/requires.txt
django_moderator.egg-info/top_level.txt
moderator/__init__.py
moderator/admin.py
moderator/constants.py
moderator/models.py
moderator/tasks.py
moderator/tests.py
moderator/utils.py
moderator/fixtures/initial_data.json
moderator/management/__init__.py
moderator/management/commands/__init__.py
moderator/management/commands/classifycomments.py
moderator/migrations/0001_initial.py
moderator/migrations/0002_auto__add_commentreply__add_cannedreply.py
moderator/migrations/0003_auto__add_field_cannedreply_site.py
moderator/migrations/0004_auto__del_field_commentreply_replied_to_comment.py
moderator/migrations/0005_auto__chg_field_commentreply_reply_comment.py
moderator/migrations/0006_auto__del_field_commentreply_reply_comment__add_field_commentreply_rep.py
moderator/migrations/0007_auto__del_field_commentreply_reply_comments.py
moderator/migrations/0007_auto__del_field_commentreply_reply_comments.pyc
moderator/migrations/0008_auto__del_classifierstate__del_word.py
moderator/migrations/0009_migrate_comment_replies.py
moderator/migrations/0010_del_commentreply_replied_to_comment_field__del_commentrepy_reply_comment_field.py
moderator/migrations/__init__.py
moderator/migrations/__init__.pyc
moderator/templates/admin/change_form.html
moderator/templates/admin/moderate.html
moderator/templates/admin/object_moderate_list.html
moderator/templates/moderator/inclusion_tags/report_comment_abuse.html
moderator/templatetags/__init__.py
moderator/templatetags/__init__.pyc
moderator/templatetags/moderator_inclusion_tags.py
moderator/templatetags/moderator_inclusion_tags.pyc